regularbot/__init__.py
regularbot/saved_data.py
regularbot-0.0.2.dist-info/METADATA
regularbot-0.0.2.dist-info/WHEEL
regularbot-0.0.2.dist-info/licenses/LICENSE
regularbot-0.0.2.dist-info/RECORD
