Metadata-Version: 2.4
Name: regularbot
Version: 0.0.2
Summary: Regularbot Python Package
Project-URL: Homepage, https://regularbot.com
Project-URL: Documentation, https://docs.regularbot.com
Author-email: Berk Karaal <iletisim.berkkaraal@gmail.com>
License-Expression: MIT
License-File: LICENSE
Classifier: Operating System :: OS Independent
Classifier: Programming Language :: Python :: 3
Requires-Python: >=3.9
